fogledgerIota/__init__.py
fogledgerIota/iota/IotaBasic.py
fogledgerIota/iota/__init__.py
fogledgerIota/iota/config/ApiConfig.py
fogledgerIota/iota/config/CoordConfig.py
fogledgerIota/iota/config/NodeConfig.py
fogledgerIota/iota/config/SpammerConfig.py
fogledgerIota/iota/config/WebAppConfig.py
fogledgerIota/iota/config/__init__.py
fogledgerIota/iota/data/api.config.local.json
fogledgerIota/iota/data/config-coo.json
fogledgerIota/iota/data/config-node.json
fogledgerIota/iota/data/config-spammer.json
fogledgerIota/iota/data/private-network.json
fogledgerIota/iota/data/private-tangle.sh
fogledgerIota/iota/data/utils.sh
fogledgerIota/iota/data/webapp.config.local.json
fogLedgerIota-1.0.3.dist-info/LICENSE.txt
fogLedgerIota-1.0.3.dist-info/METADATA
fogLedgerIota-1.0.3.dist-info/WHEEL
fogLedgerIota-1.0.3.dist-info/top_level.txt
fogLedgerIota-1.0.3.dist-info/RECORD
