Metadata-Version: 2.1
Name: fogLedgerIota
Version: 1.0.3
Summary: Plugin to build DLTs in Fogbed.
Home-page: https://github.com/larsid/FogLedger-Iota/tree/v1.0.0
Author: Weslei Santos
Author-email: weslei.eng.comp@gmail.com
Keywords: networking,emulator,protocol,Internet,dlt,iota,fog
Classifier: Programming Language :: Python :: 3
Classifier: License :: OSI Approved :: MIT License
Classifier: Operating System :: POSIX :: Linux
Classifier: Topic :: Software Development :: Testing
Classifier: Topic :: System :: Emulators
License-File: LICENSE.txt
Requires-Dist: numpy >=1.24.2
